CSVLibrary/__init__.py
robotframework_csvlibrary-0.0.5.dist-info/LICENSE
robotframework_csvlibrary-0.0.5.dist-info/METADATA
robotframework_csvlibrary-0.0.5.dist-info/WHEEL
robotframework_csvlibrary-0.0.5.dist-info/top_level.txt
robotframework_csvlibrary-0.0.5.dist-info/RECORD
