Metadata-Version: 2.1
Name: robotframework-csvlibrary
Version: 0.0.5
Summary: CSV library for Robot Framework
Home-page: https://github.com/s4int/robotframework-CSVLibrary
Author: Marcin Mierzejewski
Author-email: <mmierz@gmail.com>
License: Apache License 2.0
Keywords: robotframework testing csv
Platform: any
Classifier: Development Status :: 4 - Beta
Classifier: License :: OSI Approved :: Apache Software License
Classifier: Operating System :: OS Independent
Classifier: Programming Language :: Python
Classifier: Topic :: Software Development :: Testing
Classifier: Programming Language :: Python :: 2
Classifier: Programming Language :: Python :: 2.7
Classifier: Programming Language :: Python :: 3
Classifier: Programming Language :: Python :: 3.6
Classifier: Programming Language :: Python :: 3.7
Classifier: Programming Language :: Python :: 3.8
Classifier: Programming Language :: Python :: 3.9
Classifier: Programming Language :: Python :: 3.10
License-File: LICENSE
